{
  "version": "1.0",
  "thermal_parameters": {
    "Emissivity": 0.1,
    "AtmosphericTemperature": 20.0,
    "AtmosphericTransmission": 0.95,
    "RelativeHumidity": 0.5
  },
  "rois": [
    {
      "type": "SpotROI",
      "name": "Spot_1",
      "emissivity": 0.95,
      "x": 187.9019073569483,
      "y": 298.8555858310626,
      "radius": 30.926430517711196
    },
    {
      "type": "SpotROI",
      "name": "Spot_2",
      "emissivity": 0.95,
      "x": 380.1634877384197,
      "y": 86.97547683923705,
      "radius": 10.0
    },
    {
      "type": "PolygonROI",
      "name": "Polygon_3",
      "emissivity": 0.95,
      "points": [
        [
          384.08719346049037,
          240.00000000000003
        ],
        [
          314.76839237057203,
          212.53405994550414
        ],
        [
          231.06267029972736,
          175.91280653950957
        ],
        [
          384.08719346049037,
          162.8337874659401
        ]
      ]
    },
    {
      "type": "RectROI",
      "name": "ROI_4",
      "emissivity": 0.95,
      "x": 39,
      "y": 61,
      "width": 112.47956403269754,
      "height": 167.41144414168934
    },
    {
      "type": "SpotROI",
      "name": "Spot_5",
      "emissivity": 0.95,
      "x": 561.9618528610354,
      "y": 440.1089918256131,
      "radius": 61.00817438692093
    },
    {
      "type": "PolygonROI",
      "name": "Polygon_6",
      "emissivity": 0.95,
      "points": [
        [
          432.47956403269757,
          344.63215258855587
        ],
        [
          287.30245231607626,
          376.0217983651226
        ],
        [
          296.4577656675749,
          442.724795640327
        ],
        [
          432.47956403269757,
          344.63215258855587
        ]
      ]
    }
  ],
  "palette": "BrBG",
  "palette_inverted": true,
  "overlay_settings": {
    "scale": 0.731,
    "offset_x": -112,
    "offset_y": -42,
    "opacity": 93,
    "blend_mode": "Normal"
  }
}