{
  "version": "1.0",
  "thermal_parameters": {
    "Emissivity": 0.9,
    "AtmosphericTemperature": 20.0,
    "AtmosphericTransmission": 0.95,
    "RelativeHumidity": 0.5,
    "ObjectDistance": 3.0,
    "ReflectedApparentTemperature": 24.999994
  },
  "palette": "Grayscale",
  "palette_inverted": true,
  "temp_range_settings": {
    "mode": "manual",
    "manual_min": 30.43,
    "manual_max": 32.04
  },
  "overlay_settings": {
    "scale": 0.7405293836351845,
    "offset_x": -10,
    "offset_y": -27,
    "opacity": 100,
    "blend_mode": "Normal"
  },
  "roi_label_settings": {
    "name": true,
    "emissivity": true,
    "min": false,
    "max": true,
    "avg": true,
    "median": false
  },
  "rois": [
    {
      "type": "RectROI",
      "name": "ROI_1",
      "emissivity": 0.1,
      "x": 12,
      "y": 142,
      "width": 156.9195153507594,
      "height": 286.1581306098353
    },
    {
      "type": "SpotROI",
      "name": "Spot_2",
      "emissivity": 0.001,
      "x": 396.11198677246057,
      "y": 258.6558860667882,
      "radius": 21.537953795379508
    },
    {
      "type": "SpotROI",
      "name": "Spot_3",
      "emissivity": 0.3,
      "x": 235.60266905259556,
      "y": 136.70576280671906,
      "radius": 126.40326975476839
    },
    {
      "type": "PolygonROI",
      "name": "Polygon_4",
      "emissivity": 0.95,
      "points": [
        [
          121.79190014506894,
          356.53589320268776
        ],
        [
          215.20469242641832,
          336.5698001959871
        ],
        [
          174.55943166277774,
          320.169080940483
        ],
        [
          121.79190014506894,
          356.53589320268776
        ]
      ]
    }
  ]
}